multillm/Action.py
multillm/BaseLLM.py
multillm/DynamicClass.py
multillm/MultiLLM.py
multillm/Prompt.py
multillm/Rank.py
multillm/Redis.py
multillm/__init__.py
multillm/example.py
multillm/example_rank_callback.py
multillm/example_rank_callback3_scaled.py
multillm/rank_callback.py
multillm/utils.py
multillm/models/Codegen.py
multillm/models/Dolly.py
multillm/models/GPT.py
multillm/models/GPTJ.py
multillm/models/GPTMINI.py
multillm/models/Gemma.py
multillm/models/LLAMA2.py
multillm/models/LLAMA3.py
multillm/models/Mistral.py
multillm/models/Phi3.orig.py
multillm/models/Phi3.py
multillm/models/Zephyr.py
multillm/models/bard.py
multillm/models/claude.py
multillm/models/gemini.py
multillm-0.1024.dist-info/LICENSE
multillm-0.1024.dist-info/METADATA
multillm-0.1024.dist-info/WHEEL
multillm-0.1024.dist-info/entry_points.txt
multillm-0.1024.dist-info/top_level.txt
multillm-0.1024.dist-info/RECORD
