Metadata-Version: 2.1
Name: multillm
Version: 0.1024
Summary: VerifAI MultiLLM: A module to invoke multiple LLMs concurrently and rank their results
Author-email: VerifAI Inc <hello@verifai.ai>
Project-URL: Homepage, https://github.com/verifai/multiLLM
Project-URL: Bug Tracker, https://github.com/verifai/multiLLM
Classifier: Programming Language :: Python :: 3
Classifier: License :: OSI Approved :: MIT License
Classifier: Operating System :: OS Independent
Requires-Python: >=3.8
License-File: LICENSE
